packaging_practice/__init__.py
packaging_practice/cities.json
packaging_practice/my_file.py
packaging_practice/my_other_file.py
packaging_practice/states_info.py
packaging_practice/my_folder/__init__.py
packaging_practice/my_folder/my_nested_file.py
python_course_package_sunil-0.0.8.dist-info/METADATA
python_course_package_sunil-0.0.8.dist-info/WHEEL
python_course_package_sunil-0.0.8.dist-info/top_level.txt
python_course_package_sunil-0.0.8.dist-info/RECORD
