Metadata-Version: 2.4
Name: python-course-package-sunil
Version: 0.0.8
Summary: My package description
Author-email: sunil <some-email@gmail.com>, sunil1 <some1-email@gmail.com>
License: MIT
Keywords: one,two
Classifier: Programming Language :: Python :: 3
Requires-Python: >=3.13
Requires-Dist: numpy
Requires-Dist: importlib-metadata; python_version < "3.8"
Provides-Extra: test
Requires-Dist: pytest; extra == "test"
Requires-Dist: pytest-cov; extra == "test"
Provides-Extra: release
Requires-Dist: build; extra == "release"
Requires-Dist: twine; extra == "release"
Provides-Extra: static-code-qa
Requires-Dist: pre-commit; extra == "static-code-qa"
Provides-Extra: dev
Requires-Dist: python-course-package-sunil[release,static-code-qa,test]; extra == "dev"
